ls_django_treeadmin-0.4.8.dist-info/DESCRIPTION.rst
ls_django_treeadmin-0.4.8.dist-info/METADATA
ls_django_treeadmin-0.4.8.dist-info/RECORD
ls_django_treeadmin-0.4.8.dist-info/WHEEL
ls_django_treeadmin-0.4.8.dist-info/metadata.json
ls_django_treeadmin-0.4.8.dist-info/top_level.txt
treeadmin/__init__.py
treeadmin/admin.py
treeadmin/static/treeadmin/css/treeadmin.css
treeadmin/static/treeadmin/img/arrow-move.png
treeadmin/static/treeadmin/img/disclosure-down.png
treeadmin/static/treeadmin/img/disclosure-right.png
treeadmin/static/treeadmin/img/drag_order_circle.png
treeadmin/static/treeadmin/js/ie_compat.js
treeadmin/static/treeadmin/js/jquery-1.7.min.js
treeadmin/static/treeadmin/js/jquery-ui-1.8.16.custom.min.js
treeadmin/static/treeadmin/js/jquery.cookie.js
treeadmin/static/treeadmin/js/toolbox.js
treeadmin/static/treeadmin/js/treeadmin.js
treeadmin/templates/admin/treeadmin/tree_editor.html
