Metadata-Version: 2.0
Name: ls-django-treeadmin
Version: 0.4.8
Summary: Tree UI for mptt-managed models, extracted from FeinCMS
Home-page: https://github.com/lanshark/ls-django-treeadmin
Author: Scott Sharkey, Matthias Kestenholz  et al.
Author-email: ssharkey@lanshark.com
License: BSD
Download-URL: https://github.com/lanshark/ls-django-treeadmin/tarball/0.4.8
Platform: UNKNOWN
Classifier: Development Status :: 4 - Beta
Classifier: Framework :: Django
Classifier: Intended Audience :: Developers
Classifier: License :: OSI Approved :: BSD License
Classifier: Operating System :: OS Independent
Classifier: Programming Language :: Python :: 2.5
Classifier: Programming Language :: Python :: 2.6
Classifier: Programming Language :: Python :: 2.7
Classifier: Programming Language :: Python :: 3.4
Classifier: Programming Language :: Python :: 3.5
Classifier: Topic :: Internet :: WWW/HTTP :: Dynamic Content
Requires-Dist: Django (>=1.7)
Requires-Dist: django-mptt (>=0.5)
